oshino_redis/__init__.py
oshino_redis/agent.py
oshino_redis/version.py
oshino_redis-0.1.5.dist-info/DESCRIPTION.rst
oshino_redis-0.1.5.dist-info/METADATA
oshino_redis-0.1.5.dist-info/RECORD
oshino_redis-0.1.5.dist-info/WHEEL
oshino_redis-0.1.5.dist-info/metadata.json
oshino_redis-0.1.5.dist-info/top_level.txt
