Metadata-Version: 2.0
Name: oshino-redis
Version: 0.1.5
Summary: ...
Home-page: UNKNOWN
Author: zaibacu
Author-email: UNKNOWN
License: UNKNOWN
Platform: UNKNOWN
Requires-Dist: aioredis
Requires-Dist: oshino
